logaid/__init__.py
logaid/log.py
logaid/mailer.py
logaid-1.5.1.dist-info/licenses/LICENSE
logaid-1.5.1.dist-info/METADATA
logaid-1.5.1.dist-info/WHEEL
logaid-1.5.1.dist-info/top_level.txt
logaid-1.5.1.dist-info/RECORD
