Metadata-Version: 2.4
Name: logaid
Version: 1.5.1
Summary: A log aid for you.
Author: BreezeSun
License: MIT
License-File: LICENSE
Dynamic: author
Dynamic: description
Dynamic: description-content-type
Dynamic: license
Dynamic: license-file
Dynamic: summary
